{
  "name": "Dimensity8000/8100.V1",
  "author": "Nalanyinyun",
  "configVersion": 4,
  "debug": false,
  "CpuGovernor": {
    "enable": true,
    "slowSampleTime": 60,
    "fastSampleTime": 40,
    "policy": {
      "policyNum": 3,
      "policy0": {
        "cpus": "0-3",
        "freqTablePath": "/sys/devices/system/cpu/cpu0/cpufreq/scaling_available_frequencies",
        "cpuCapacity": 284,
        "lowPowerFreq": 450,
        "basicFreq": 1500,
        "expectFreq": 1300,
        "modelFreq": 2000,
        "modelPower": 300
      },
      "policy1": {
        "cpus": "4-6",
        "freqTablePath": "/sys/devices/system/cpu/cpu4/cpufreq/scaling_available_frequencies",
        "cpuCapacity": 1024,
        "lowPowerFreq": 700,
        "basicFreq": 1200,
        "expectFreq": 1900,
        "modelFreq": 2850,
        "modelPower": 1610
      },
      "policy2": {
        "cpus": "7-7",
        "freqTablePath": "/sys/devices/system/cpu/cpu7/cpufreq/scaling_available_frequencies",
        "cpuCapacity": 1024,
        "lowPowerFreq": 800,
        "basicFreq": 1000,
        "expectFreq": 2200,
        "modelFreq": 2850,
        "modelPower": 1610
      }
    },
    "powersave": {
      "powerLimit": 2700,
      "policy0": {
        "upRateLatency": 150,
        "perfMargin": 17
      },
      "policy1": {
        "upRateLatency": 200,
        "perfMargin": 10
      },
      "policy2": {
        "upRateLatency": 200,
        "perfMargin": 10
      },
      "freqBurst": {
        "touch": {
          "boost": 15,
          "durationTime": 500
        },
        "swipe": {
          "boost": 10,
          "durationTime": 300
        },
        "gesture": {
          "boost": 15,
          "durationTime": 300
        },
        "heavyload": {
          "boost": 10,
          "durationTime": 3000
        }
      }
    },
    "balance": {
      "powerLimit": 3500,
      "policy0": {
        "upRateLatency": 100,
        "perfMargin": 20
      },
      "policy1": {
        "upRateLatency": 130,
        "perfMargin": 20
      },
      "policy2": {
        "upRateLatency": 150,
        "perfMargin": 10
      },
      "freqBurst": {
        "touch": {
          "boost": 20,
          "durationTime": 500
        },
        "swipe": {
          "boost": 10,
          "durationTime": 500
        },
        "gesture": {
          "boost": 20,
          "durationTime": 300
        },
        "heavyload": {
          "boost": 10,
          "durationTime": 3000
        }
      }
    },
    "performance": {
      "powerLimit": 5000,
      "policy0": {
        "upRateLatency": 100,
        "perfMargin": 25
      },
      "policy1": {
        "upRateLatency": 150,
        "perfMargin": 20
      },
      "policy2": {
        "upRateLatency": 150,
        "perfMargin": 20
      },
      "freqBurst": {
        "touch": {
          "boost": 40,
          "durationTime": 200
        },
        "swipe": {
          "boost": 30,
          "durationTime": 700
        },
        "gesture": {
          "boost": 20,
          "durationTime": 300
        },
        "heavyload": {
          "boost": 20,
          "durationTime": 4000
        }
      }
    },
    "fast": {
      "powerLimit": 7000,
      "policy0": {
        "upRateLatency": 90,
        "perfMargin": 40
      },
      "policy1": {
        "upRateLatency": 100,
        "perfMargin": 30
      },
      "policy2": {
        "upRateLatency": 90,
        "perfMargin": 30
      },
      "freqBurst": {
        "touch": {
          "boost": 50,
          "durationTime": 400
        },
        "swipe": {
          "boost": 50,
          "durationTime": 900
        },
        "gesture": {
          "boost": 20,
          "durationTime": 500
        },
        "heavyload": {
          "boost": 20,
          "durationTime": 5000
        }
      }
    }
  },
  "ThreadSchedOpt": {
    "enable": true,
    "MainThread": {
      "cpus": "456",
      "nice": -12
    },
    "GameSingleThread": {
      "cpus": "7",
      "nice": -16
    },
    "GameMultiThread": {
      "cpus": "456",
      "nice": -16
    },
    "RenderThread": {
      "cpus": "7",
      "nice": -20
    },
    "UIThread": {
      "cpus": "456",
      "nice": -12
    },
    "MediaThread": {
      "cpus": "012345",
      "nice": -16
    },
    "WebViewThread": {
      "cpus": "456",
      "nice": -12
    },
    "ProcessThread": {
      "cpus": "456",
      "nice": -8
    },
    "NonRealTimeThread": {
      "cpus": "0123",
      "nice": 0
    },
    "OtherThread": {
      "cpus": "0123456",
      "nice": -4
    }
  },
  "MtkGpuGovernor": {
    "enable": true,
    "slowSampleTime": 60,
    "fastSampleTime": 40,
    "powersave": {
      "maxFreq": 402,
      "perfMargin": 20,
      "upRateLatency": 80
    },
    "balance": {
      "maxFreq": 453,
      "perfMargin": 20,
      "upRateLatency": 80
    },
    "performance": {
      "maxFreq": 555,
      "perfMargin": 25,
      "upRateLatency": 60
    },
    "fast": {
      "maxFreq": 852,
      "perfMargin": 30,
      "upRateLatency": 40
    }
  }
}